odoo/addons/project_stock_product_set/README.rst
odoo/addons/project_stock_product_set/__init__.py
odoo/addons/project_stock_product_set/__manifest__.py
odoo/addons/project_stock_product_set/i18n/es.po
odoo/addons/project_stock_product_set/i18n/project_stock_product_set.pot
odoo/addons/project_stock_product_set/models/__init__.py
odoo/addons/project_stock_product_set/models/product_set_line.py
odoo/addons/project_stock_product_set/readme/CONFIGURE.rst
odoo/addons/project_stock_product_set/readme/CONTRIBUTORS.rst
odoo/addons/project_stock_product_set/readme/DESCRIPTION.rst
odoo/addons/project_stock_product_set/readme/USAGE.rst
odoo/addons/project_stock_product_set/static/description/icon.png
odoo/addons/project_stock_product_set/static/description/index.html
odoo/addons/project_stock_product_set/tests/__init__.py
odoo/addons/project_stock_product_set/tests/test_project_stock_product_set.py
odoo/addons/project_stock_product_set/views/project_task_view.xml
odoo/addons/project_stock_product_set/wizard/__init__.py
odoo/addons/project_stock_product_set/wizard/product_set_add.py
odoo/addons/project_stock_product_set/wizard/product_set_add.xml
odoo13_addon_project_stock_product_set-13.0.1.0.2.dist-info/METADATA
odoo13_addon_project_stock_product_set-13.0.1.0.2.dist-info/WHEEL
odoo13_addon_project_stock_product_set-13.0.1.0.2.dist-info/top_level.txt
odoo13_addon_project_stock_product_set-13.0.1.0.2.dist-info/RECORD
