Metadata-Version: 2.1
Name: odoo13-addon-project-stock-product-set
Version: 13.0.1.0.2
Summary: Project Stock Product Set
Home-page: https://github.com/OCA/project
Author: Tecnativa, Odoo Community Association (OCA)
Author-email: support@odoo-community.org
License: AGPL-3
Platform: UNKNOWN
Classifier: Programming Language :: Python
Classifier: Framework :: Odoo
Classifier: Framework :: Odoo :: 13.0
Classifier: License :: OSI Approved :: GNU Affero General Public License v3
Requires-Python: >=3.5
Requires-Dist: odoo13-addon-project-stock
Requires-Dist: odoo13-addon-sale-product-set
Requires-Dist: odoo (<13.1dev,>=13.0a)
